{
    "bookshelf:load_conditions": [
        {
            "type": "bookshelf:item_exists",
            "values": [
                "bloomingnature:bottlebrushes"
            ]
        }
    ],
    "type": "botanypots:crop",
    "seed": {
        "item": "bloomingnature:bottlebrushes"
    },
    "categories": [
        "dirt"
    ],
    "growthTicks": 1200,
    "display": {
        "block": "bloomingnature:bottlebrushes"
    },
    "drops": [
        {
            "chance": 1.00,
            "output": {
                "item": "bloomingnature:bottlebrushes"
            }
        }
    ]
}